excerpt_tool/__init__.py
excerpt_tool/core.py
excerpt_tool/main.py
excerpt_tool-0.0.4.dist-info/LICENSE
excerpt_tool-0.0.4.dist-info/METADATA
excerpt_tool-0.0.4.dist-info/WHEEL
excerpt_tool-0.0.4.dist-info/entry_points.txt
excerpt_tool-0.0.4.dist-info/top_level.txt
excerpt_tool-0.0.4.dist-info/RECORD
