Metadata-Version: 2.1
Name: excerpt-tool
Version: 0.0.4
Summary: 一个摘录软件
Home-page: https://github.com/Mryan2005/excerpt_tool
Author: Mryan2005
License: UNKNOWN
Platform: UNKNOWN
License-File: LICENSE
